{
  "users": [
    {
      "id": "893e",
      "name": "juan jose ",
      "correo": "juanjo@gmail.com",
      "password": "123",
      "typePerson": "persona"
    },
    {
      "id": "c89c",
      "name": "ricardo",
      "correo": "ricardo@gmail.com",
      "password": "123",
      "typePerson": "empresa"
    },
    {
      "id": "12f7",
      "name": "mamaguevo company",
      "correo": "robinson@gmail.com",
      "password": "123",
      "typePerson": "empresa"
    },
    {
      "id": "06d3",
      "name": "cambios envigado",
      "correo": "cambios@gmail.com",
      "password": "123",
      "typePerson": "empresa",
      "profileCompany": {
        "nameCompanyProfile": "jobbridge",
        "sectorCompanyProfile": "busqueda de empleo",
        "industryCompanyProfile": "servicio web",
        "descriptionCompanyProfile": "En nuestra plataforma, conectamos empresas que buscan talento con personas en busca de nuevas oportunidades\nlaborales. Ya seas una empresa en crecimiento o un profesional en busca de empleo, aquí encontrarás un\nespacio seguro y eficiente para satisfacer tus necesidades.",
        "addressCompanyProfile": "cll 83 #58-19 "
      }
    }
  ]
}